README.rst
setup.py
siftpy/__init__.py
siftpy/_builders.py
siftpy/_choice.py
siftpy/_context_extractor.py
siftpy/_exceptions.py
siftpy/_providers.py
siftpy/_reducer.py
siftpy/_sift.py
siftpy/_validators.py
siftpy/configuration.py
siftpy.egg-info/PKG-INFO
siftpy.egg-info/SOURCES.txt
siftpy.egg-info/dependency_links.txt
siftpy.egg-info/entry_points.txt
siftpy.egg-info/top_level.txt
siftpy/_util/__init__.py
siftpy/_util/helpers.py
siftpy/_util/printers.py