Metadata-Version: 1.1
Name: siftpy
Version: 0.0.10
Summary: A Python module for filtering object collections through data-driven filter definitions.
Home-page: https://github.com/tckerr/siftpy
Author: Thomas Kerr
Author-email: tckerr@gmail.com
License: MIT
Keywords: development objects filtering data graphs
Platform: UNKNOWN
Classifier: Development Status :: 3 - Alpha
Classifier: Intended Audience :: Developers
Classifier: Topic :: Software Development
Classifier: License :: OSI Approved :: MIT License
Classifier: Programming Language :: Python :: 2
Classifier: Programming Language :: Python :: 2.7
Classifier: Programming Language :: Python :: 3
Classifier: Programming Language :: Python :: 3.3
Classifier: Programming Language :: Python :: 3.4
Classifier: Programming Language :: Python :: 3.5
